Programs/Calcualtor.py
Programs/Emoji_Converter.py
Programs/Password_Generator.py
Programs/__init__.py
Programs/Word_Guessing/MAIN_Word_Guessing.py
Programs/Word_Guessing/Word_Guess1.py
Programs/Word_Guessing/Word_Guess2.py
Programs/Word_Guessing/__init__.py
Programs/Word_Guessing/words.py
Programs/card_creator_2/__init__.py
Programs/card_creator_2/card_creator.py
Programs/card_creator_2/utilities.py
Programs/contact_book/Contact.py
Programs/contact_book/__init__.py
km_projects-0.1.dist-info/LICENSE.txt
km_projects-0.1.dist-info/METADATA
km_projects-0.1.dist-info/WHEEL
km_projects-0.1.dist-info/top_level.txt
km_projects-0.1.dist-info/RECORD
