Metadata-Version: 2.1
Name: km_projects
Version: 0.1
Summary: My Python creations
Author: Kodjo Messie
Author-email: kodjomessie@gmail.com
Classifier: Programming Language :: Python :: 3
Classifier: License :: OSI Approved :: MIT License
Classifier: Operating System :: OS Independent
License-File: LICENSE.txt
